yokedcache/__init__.py
yokedcache/__main__.py
yokedcache/cache.py
yokedcache/circuit_breaker.py
yokedcache/cli.py
yokedcache/config.py
yokedcache/decorators.py
yokedcache/exceptions.py
yokedcache/metrics.py
yokedcache/middleware.py
yokedcache/models.py
yokedcache/monitoring.py
yokedcache/routing.py
yokedcache/swr.py
yokedcache/tracing.py
yokedcache/utils.py
yokedcache/vector_search.py
yokedcache/backends/__init__.py
yokedcache/backends/base.py
yokedcache/backends/disk.py
yokedcache/backends/memcached.py
yokedcache/backends/memory.py
yokedcache/backends/redis.py
yokedcache/backends/sqlite.py
yokedcache-0.3.0.dist-info/METADATA
yokedcache-0.3.0.dist-info/WHEEL
yokedcache-0.3.0.dist-info/entry_points.txt
yokedcache-0.3.0.dist-info/licenses/LICENSE
yokedcache-0.3.0.dist-info/RECORD
