Metadata-Version: 2.4
Name: yokedcache
Version: 0.3.0
Summary: Python caching library for FastAPI with Redis auto-invalidation, vector search caching, and intelligent cache management
Project-URL: Homepage, https://github.com/sirstig/yokedcache
Project-URL: Documentation, https://sirstig.github.io/yokedcache
Project-URL: Repository, https://github.com/sirstig/yokedcache
Project-URL: Bug Tracker, https://github.com/sirstig/yokedcache/issues
Author: Project Yoked LLC
License-Expression: MIT
License-File: LICENSE
Keywords: async caching,cache,cache auto-invalidation,cache invalidation,cache management,caching,database,database caching,fastapi,fastapi caching,fastapi redis,intelligent caching,memcached,orm,performance,python caching library,python redis,redis,redis caching,sqlalchemy,vector search caching
Classifier: Development Status :: 4 - Beta
Classifier: Environment :: Web Environment
Classifier: Framework :: AsyncIO
Classifier: Framework :: FastAPI
Classifier: Intended Audience :: Developers
Classifier: Intended Audience :: System Administrators
Classifier: License :: OSI Approved :: MIT License
Classifier: Operating System :: OS Independent
Classifier: Programming Language :: Python :: 3
Classifier: Programming Language :: Python :: 3.9
Classifier: Programming Language :: Python :: 3.10
Classifier: Programming Language :: Python :: 3.11
Classifier: Programming Language :: Python :: 3.12
Classifier: Topic :: Database
Classifier: Topic :: Database :: Front-Ends
Classifier: Topic :: Internet :: WWW/HTTP :: Dynamic Content
Classifier: Topic :: Internet :: WWW/HTTP :: HTTP Servers
Classifier: Topic :: Software Development :: Libraries
Classifier: Topic :: Software Development :: Libraries :: Application Frameworks
Classifier: Topic :: Software Development :: Libraries :: Python Modules
Classifier: Topic :: System :: Distributed Computing
Requires-Python: >=3.9
Requires-Dist: click>=8.0.0
Requires-Dist: fastapi>=0.68.0
Requires-Dist: pyyaml>=6.0
Requires-Dist: redis>=4.0.0
Requires-Dist: typing-extensions>=4.0.0
Provides-Extra: dev
Requires-Dist: aiomcache<1.0.0,>=0.8.0; extra == 'dev'
Requires-Dist: aiosqlite>=0.19.0; extra == 'dev'
Requires-Dist: black>=22.0.0; extra == 'dev'
Requires-Dist: diskcache>=5.6.0; extra == 'dev'
Requires-Dist: fakeredis>=2.0.0; extra == 'dev'
Requires-Dist: flake8>=4.0.0; extra == 'dev'
Requires-Dist: fuzzywuzzy>=0.18.0; extra == 'dev'
Requires-Dist: httpx>=0.24.0; extra == 'dev'
Requires-Dist: isort>=5.10.0; extra == 'dev'
Requires-Dist: mypy>=1.0.0; extra == 'dev'
Requires-Dist: numpy>=1.21.0; extra == 'dev'
Requires-Dist: opentelemetry-api>=1.24.0; extra == 'dev'
Requires-Dist: opentelemetry-sdk>=1.24.0; extra == 'dev'
Requires-Dist: pre-commit>=2.20.0; extra == 'dev'
Requires-Dist: prometheus-client>=0.16.0; extra == 'dev'
Requires-Dist: pytest-asyncio>=0.21.0; extra == 'dev'
Requires-Dist: pytest-cov>=4.0.0; extra == 'dev'
Requires-Dist: pytest>=7.0.0; extra == 'dev'
Requires-Dist: python-levenshtein>=0.12.0; extra == 'dev'
Requires-Dist: scikit-learn>=1.0.0; extra == 'dev'
Requires-Dist: scipy>=1.7.0; extra == 'dev'
Requires-Dist: statsd>=4.0.0; extra == 'dev'
Requires-Dist: types-pyyaml>=6.0.0; extra == 'dev'
Requires-Dist: types-redis>=4.0.0; extra == 'dev'
Provides-Extra: disk
Requires-Dist: diskcache>=5.0.0; extra == 'disk'
Provides-Extra: docs
Requires-Dist: mkdocs-material>=9.0.0; extra == 'docs'
Requires-Dist: mkdocs>=1.4.0; extra == 'docs'
Requires-Dist: mkdocstrings[python]>=0.20.0; extra == 'docs'
Provides-Extra: full
Requires-Dist: aiomcache<1.0.0,>=0.8.0; extra == 'full'
Requires-Dist: aiosqlite>=0.19.0; extra == 'full'
Requires-Dist: diskcache>=5.0.0; extra == 'full'
Requires-Dist: fuzzywuzzy>=0.18.0; extra == 'full'
Requires-Dist: numpy>=1.21.0; extra == 'full'
Requires-Dist: opentelemetry-api>=1.15.0; extra == 'full'
Requires-Dist: opentelemetry-sdk>=1.15.0; extra == 'full'
Requires-Dist: prometheus-client>=0.16.0; extra == 'full'
Requires-Dist: python-levenshtein>=0.12.0; extra == 'full'
Requires-Dist: scikit-learn>=1.0.0; extra == 'full'
Requires-Dist: scipy>=1.7.0; extra == 'full'
Requires-Dist: sqlalchemy>=1.4.0; extra == 'full'
Requires-Dist: statsd>=4.0.0; extra == 'full'
Provides-Extra: fuzzy
Requires-Dist: fuzzywuzzy>=0.18.0; extra == 'fuzzy'
Requires-Dist: python-levenshtein>=0.12.0; extra == 'fuzzy'
Provides-Extra: memcached
Requires-Dist: aiomcache<1.0.0,>=0.8.0; extra == 'memcached'
Provides-Extra: monitoring
Requires-Dist: prometheus-client>=0.16.0; extra == 'monitoring'
Requires-Dist: statsd>=4.0.0; extra == 'monitoring'
Provides-Extra: sqlalchemy
Requires-Dist: sqlalchemy>=1.4.0; extra == 'sqlalchemy'
Provides-Extra: sqlite
Requires-Dist: aiosqlite>=0.19.0; extra == 'sqlite'
Provides-Extra: tracing
Requires-Dist: opentelemetry-api>=1.15.0; extra == 'tracing'
Requires-Dist: opentelemetry-sdk>=1.15.0; extra == 'tracing'
Provides-Extra: vector
Requires-Dist: numpy>=1.21.0; extra == 'vector'
Requires-Dist: scikit-learn>=1.0.0; extra == 'vector'
Requires-Dist: scipy>=1.7.0; extra == 'vector'
